odoo8_addon_partner_sale_risk-8.0.1.0.0-py2.7-nspkg.pth
odoo8_addon_partner_sale_risk-8.0.1.0.0.dist-info/DESCRIPTION.rst
odoo8_addon_partner_sale_risk-8.0.1.0.0.dist-info/METADATA
odoo8_addon_partner_sale_risk-8.0.1.0.0.dist-info/RECORD
odoo8_addon_partner_sale_risk-8.0.1.0.0.dist-info/WHEEL
odoo8_addon_partner_sale_risk-8.0.1.0.0.dist-info/metadata.json
odoo8_addon_partner_sale_risk-8.0.1.0.0.dist-info/namespace_packages.txt
odoo8_addon_partner_sale_risk-8.0.1.0.0.dist-info/top_level.txt
odoo_addons/partner_sale_risk/README.rst
odoo_addons/partner_sale_risk/__init__.py
odoo_addons/partner_sale_risk/__openerp__.py
odoo_addons/partner_sale_risk/models/__init__.py
odoo_addons/partner_sale_risk/models/res_partner.py
odoo_addons/partner_sale_risk/models/sale.py
odoo_addons/partner_sale_risk/tests/__init__.py
odoo_addons/partner_sale_risk/tests/test_partner_sale_risk.py
odoo_addons/partner_sale_risk/views/res_partner_view.xml
odoo_addons/partner_sale_risk/views/sale_view.xml
